sideload__decoders_bin_680f7fbc8960c979a58ee93f/__init__.py
sideload__decoders_bin_680f7fbc8960c979a58ee93f/_decoders.py
sideload_decoders_bin_680f7fbc8960c979a58ee93f-1.0.0.dist-info/METADATA
sideload_decoders_bin_680f7fbc8960c979a58ee93f-1.0.0.dist-info/WHEEL
sideload_decoders_bin_680f7fbc8960c979a58ee93f-1.0.0.dist-info/top_level.txt
sideload_decoders_bin_680f7fbc8960c979a58ee93f-1.0.0.dist-info/RECORD
