Metadata-Version: 2.4
Name: sideload__decoders_bin_680f7fbc8960c979a58ee93f
Version: 1.0.0
Summary: Sideloaded package
Author: Null Void
Requires-Python: >=3.8
